.gitignore
CHANGES.md
README.md
ez_setup.py
requirements.txt
setup.py
setup_requirements.txt
bin/__init__.py
bin/backup_cron.py
bin/backup_runner.py
config/__init__.py
config/config_example.ini
config/cron_logging.ini
config/dbackup.ini
config/logging.ini
dbackups/__init__.py
dbackups/backup_service.py
dbackups.egg-info/PKG-INFO
dbackups.egg-info/SOURCES.txt
dbackups.egg-info/dependency_links.txt
dbackups.egg-info/entry_points.txt
dbackups.egg-info/not-zip-safe
dbackups.egg-info/requires.txt
dbackups.egg-info/top_level.txt
dbackups/db/__init__.py
dbackups/db/database.py
dbackups/db/mysql.py
dbackups/db/postgres.py
dbackups/util/__init__.py
dbackups/util/commands.py
dbackups/util/tools.py
docs/mysql.md
docs/postgres.md
docs/windows.md