Metadata-Version: 1.0
Name: dbackups
Version: 0.5.4
Summary: A simple python application that makes database backups a little easier.
Home-page: https://github.com/jeffbean/dbackups
Author: Jeffrey Bean
Author-email: jrb3330@gmail.com
License: UNKNOWN
Platform: UNKNOWN
